env_protector/__init__.py
env_protector/hooks_manager.py
env_protector-0.2.1.dist-info/METADATA
env_protector-0.2.1.dist-info/WHEEL
env_protector-0.2.1.dist-info/entry_points.txt
env_protector-0.2.1.dist-info/top_level.txt
env_protector-0.2.1.dist-info/RECORD
