Metadata-Version: 2.1
Name: env-protector
Version: 0.2.1
Summary: Package for managing Git hooks to encrypt and decrypt .env files.
Home-page: https://github.com/lechplace/env-protector
Author: Lech Hubicki
Author-email: lech.hubicki@gmail.com
License: UNKNOWN
Platform: UNKNOWN
Classifier: Programming Language :: Python :: 3
Classifier: License :: OSI Approved :: MIT License
Classifier: Operating System :: OS Independent
Requires-Python: >=3.6
